quant_risk/__init__.py
quant_risk/models/__init__.py
quant_risk/models/regression.py
quant_risk/models/time_series.py
quant_risk/portfolio/__init__.py
quant_risk/portfolio/mean_variance.py
quant_risk/portfolio/portfolio.py
quant_risk/portfolio/regime_signal.py
quant_risk/portfolio/risk_parity.py
quant_risk/statistics/VaR.py
quant_risk/statistics/__init__.py
quant_risk/statistics/annualize.py
quant_risk/statistics/financial_ratios.py
quant_risk/statistics/statistics.py
quant_risk/statistics/stats.py
quant_risk/statistics/summarize.py
quant_risk/statistics/tests.py
quant_risk/utils/__init__.py
quant_risk/utils/backtest.py
quant_risk/utils/plot.py
quant_risk-1.1.1.dist-info/LICENSE
quant_risk-1.1.1.dist-info/METADATA
quant_risk-1.1.1.dist-info/WHEEL
quant_risk-1.1.1.dist-info/top_level.txt
quant_risk-1.1.1.dist-info/RECORD
