Metadata-Version: 2.1
Name: quant-risk
Version: 1.1.1
Summary: Quantitative functions in Python
Home-page: https://github.com/QAM-ATC/Risk/tree/package
Author: NTU Quantitative Asset Management Club
Author-email: quantassetmgmtdivision@gmail.com
License: MIT
Keywords: Quantitative,Risk,Portfolio
Platform: UNKNOWN
Requires-Dist: statsmodels (==0.12.2)
Requires-Dist: empyrical (==0.5.5)
Requires-Dist: matplotlib (==3.4.2)
Requires-Dist: pyportfolioopt (==1.4.2)
Requires-Dist: sklearn
Requires-Dist: pandas
Requires-Dist: numpy
